proj2md/__init__.py
proj2md/cli.py
proj2md-0.1.0.dist-info/licenses/LICENSE
proj2md-0.1.0.dist-info/METADATA
proj2md-0.1.0.dist-info/WHEEL
proj2md-0.1.0.dist-info/entry_points.txt
proj2md-0.1.0.dist-info/top_level.txt
proj2md-0.1.0.dist-info/RECORD
