Metadata-Version: 2.4
Name: proj2md
Version: 0.1.0
Summary: Generate a comprehensive Markdown document for any project directory via CLI
Author-email: Thibaud Perrin <thibaud.perrin6@gmail.com>
Project-URL: Homepage, https://github.com/thibaud-perrin/proj2md
Project-URL: Documentation, https://github.com/thibaud-perrin/proj2md
Project-URL: Issues, https://github.com/thibaud-perrin/proj2md/issues
Keywords: llm,markdown,project structure
Classifier: Development Status :: 3 - Alpha
Classifier: Intended Audience :: Developers
Classifier: Operating System :: OS Independent
Classifier: Topic :: Software Development :: Libraries
Classifier: Programming Language :: Python
Classifier: Programming Language :: Python :: 3.10
Classifier: Programming Language :: Python :: 3.11
Classifier: Programming Language :: Python :: 3.12
Classifier: Programming Language :: Python :: 3.13
Classifier: Programming Language :: Python :: 3 :: Only
Classifier: License :: Other/Proprietary License
Requires-Python: >=3.10
License-File: LICENSE
Requires-Dist: click>=8.0.0
Requires-Dist: tomli>=2.0.0
Provides-Extra: dev
Requires-Dist: pytest>=8.3.4; extra == "dev"
Requires-Dist: pytest-asyncio>=0.26.0; extra == "dev"
Requires-Dist: pytest-cov>=6.1.0; extra == "dev"
Requires-Dist: typos>=1.31.1; extra == "dev"
Requires-Dist: ruff>=0.11.2; extra == "dev"
Requires-Dist: mypy>=1.15.0; extra == "dev"
Requires-Dist: pyright>=1.1.398; extra == "dev"
Requires-Dist: pre-commit>=4.2.0; extra == "dev"
Requires-Dist: bump2version>=1.0.1; extra == "dev"
Requires-Dist: build>=1.2.2; extra == "dev"
Requires-Dist: twine>=6.1.0; extra == "dev"
Dynamic: license-file
